{
  "GPIO": {
    "AIP1640": "aip1640",
    "Button": "button",
    "Buzzer": "buzzer",
    "Direct Pin": "direct-pin",
    "Grove Button": "grove-button",
    "Grove Buzzer": "grove-buzzer",
    "Grove Led": "grove-led",
    "Grove Vibration Sensor": "grove-piezo-vibration-sensor",
    "Grove Relay": "grove-relay",
    "Grove Touch": "grove-touch",
    "LED": "led",
    "Makey Button": "makey-button",
    "Motor": "motor",
    "PIR Motion Sensor": "pir-motion-sensor",
    "Relay": "relay",
    "RGB LED": "rgb-led",
    "Servo": "servo",
    "Stepper": "stepper",
    "TM1638": "tm1638"
  },

  "AIO": {
    "Analog Sensor": "analog-sensor",
    "Grove Light Sensor": "grove-light-sensor",
    "Grove Rotary": "grove-rotary",
    "Grove Sound Sensor": "grove-sound-sensor",
    "Grove Temperature Sensor": "grove-temperature-sensor"
  },

  "I2C": {
    "Adafruit Motor HAT": "adafruit-motor-hat",
    "ADS1015": "ads1015",
    "ADS1115": "ads1115",
    "BlinkM": "blinkm",
    "BME280": "bme280",
    "BMP180": "bmp180",
    "BMP280": "bmp280",
    "DRV2605L": "drv2605l",
    "Grove LCD w/RGB": "grove-lcd",
    "Grove Accelerometer": "grove-accelerometer",
    "HMC6352 Compass": "hmc6352-compass",
    "INA3221": "ina3221",
    "JHD1313M1": "jhd1313m1",
    "L3GD20H": "l3gd20h",
    "LIDAR-Lite": "lidar-lite",
    "MCP23017": "mcp23017",
    "MMA7660": "mma7660",
    "MPL115A2": "mpl115a2",
    "MPU6050": "mpu6050",
    "PCA9685": "pca9685",
    "SHT3X": "sht3x",
    "SSD1306": "ssd1306",
    "TSL2561": "tsl2561",
    "Wiimote Nunchuk": "wiimote-nunchuk"
  },

  "SPI": {
    "APA102": "apa102",
    "MCP3002": "mcp3002",
    "MCP3004": "mcp3004",
    "MCP3008": "mcp3008",
    "MCP3202": "mcp3202",
    "MCP3204": "mcp3204",
    "MCP3208": "mcp3208",
    "MCP3304": "mcp3304"
  },

  "BLE": {
    "Battery Service": "ble-battery",
    "Device Information Service": "ble-device-information",
    "Generic Access Service": "ble-generic-access"
  },

  "Microbit": {
    "Accelerometer Service": "microbit-accelerometer",
    "Button Service": "microbit-button",
    "IOPin Service": "microbit-iopin",
    "LED Service": "microbit-led",
    "Magnetometer Service": "microbit-magnetometer",
    "Temperature Service": "microbit-temperature"
  },

  "ARDrone - Flight": "ardrone-flight",
  "Bebop": "bebop",
  "CurieIMU": "curieimu",
  "DJI Tello": "tello",
  "GoPiGo3": "gopigo3",
  "HS-200": "hs200",
  "Joystick - DualShock 3": "dualshock3",
  "Joystick - Xbox 360": "xbox360",
  "Keyboard": "keyboard",
  "Leap Motion": "leapmotion",
  "Mavlink": "mavlink",
  "Minidrone": "minidrone",
  "MQTT": "mqtt",
  "NATS": "nats",
  "Neurosky Mindwave": "neurosky",
  "Pebble": "pebble",
  "Sphero": "sphero",
  "SPRK+": "sprkplus",
  "BB-8": "bb8",
  "Ollie": "ollie"
}
